ShengcaiYoushuZhishiXingqiuZhengli20190928/README.md
ShengcaiYoushuZhishiXingqiuZhengli20190928/__init__.py
ShengcaiYoushuZhishiXingqiuZhengli20190928/__main__.py
ShengcaiYoushuZhishiXingqiuZhengli20190928/file.epub
ShengcaiYoushuZhishiXingqiuZhengli20190928/index.html
ShengcaiYoushuZhishiXingqiuZhengli20190928/css/__init__.py
ShengcaiYoushuZhishiXingqiuZhengli20190928/css/annotations.css
ShengcaiYoushuZhishiXingqiuZhengli20190928/css/main.css
ShengcaiYoushuZhishiXingqiuZhengli20190928/css/normalize.css
ShengcaiYoushuZhishiXingqiuZhengli20190928/css/popup.css
ShengcaiYoushuZhishiXingqiuZhengli20190928/font/__init__.py
ShengcaiYoushuZhishiXingqiuZhengli20190928/font/fontello.eot
ShengcaiYoushuZhishiXingqiuZhengli20190928/font/fontello.svg
ShengcaiYoushuZhishiXingqiuZhengli20190928/font/fontello.ttf
ShengcaiYoushuZhishiXingqiuZhengli20190928/font/fontello.woff
ShengcaiYoushuZhishiXingqiuZhengli20190928/img/__init__.py
ShengcaiYoushuZhishiXingqiuZhengli20190928/img/annotator-glyph-sprite.png
ShengcaiYoushuZhishiXingqiuZhengli20190928/img/annotator-icon-sprite.png
ShengcaiYoushuZhishiXingqiuZhengli20190928/img/apple-touch-icon.png
ShengcaiYoushuZhishiXingqiuZhengli20190928/img/cancelfullscreen.png
ShengcaiYoushuZhishiXingqiuZhengli20190928/img/close.png
ShengcaiYoushuZhishiXingqiuZhengli20190928/img/fullscreen.png
ShengcaiYoushuZhishiXingqiuZhengli20190928/img/loader.gif
ShengcaiYoushuZhishiXingqiuZhengli20190928/img/menu-icon.png
ShengcaiYoushuZhishiXingqiuZhengli20190928/img/save.png
ShengcaiYoushuZhishiXingqiuZhengli20190928/img/saved.png
ShengcaiYoushuZhishiXingqiuZhengli20190928/img/settings-s.png
ShengcaiYoushuZhishiXingqiuZhengli20190928/img/settings.png
ShengcaiYoushuZhishiXingqiuZhengli20190928/img/star.png
ShengcaiYoushuZhishiXingqiuZhengli20190928/js/__init__.py
ShengcaiYoushuZhishiXingqiuZhengli20190928/js/epub.js
ShengcaiYoushuZhishiXingqiuZhengli20190928/js/epub.min.js
ShengcaiYoushuZhishiXingqiuZhengli20190928/js/epub.min.map
shengcai_youshu_zhishi_xingqiu_zhengli_20190928-2024.3.4.0.dist-info/METADATA
shengcai_youshu_zhishi_xingqiu_zhengli_20190928-2024.3.4.0.dist-info/WHEEL
shengcai_youshu_zhishi_xingqiu_zhengli_20190928-2024.3.4.0.dist-info/entry_points.txt
shengcai_youshu_zhishi_xingqiu_zhengli_20190928-2024.3.4.0.dist-info/top_level.txt
shengcai_youshu_zhishi_xingqiu_zhengli_20190928-2024.3.4.0.dist-info/RECORD
